test_helpers/__init__.py
test_helpers/bases.py
test_helpers/compat.py
test_helpers/mongo.py
test_helpers/postgres.py
test_helpers/rabbit.py
test_helpers/url.py
test_helpers/utils.py
test_helpers/mixins/__init__.py
test_helpers/mixins/environment.py
test_helpers/mixins/patch_mixin.py
test_helpers/mixins/tornado.py
test_helpers-1.6.0.dist-info/DESCRIPTION.rst
test_helpers-1.6.0.dist-info/METADATA
test_helpers-1.6.0.dist-info/RECORD
test_helpers-1.6.0.dist-info/WHEEL
test_helpers-1.6.0.dist-info/entry_points.txt
test_helpers-1.6.0.dist-info/metadata.json
test_helpers-1.6.0.dist-info/top_level.txt
