Metadata-Version: 2.0
Name: test-helpers
Version: 1.6.0
Summary: A collection of test helpers to facilitate AAA testing.
Home-page: UNKNOWN
Author: AWeber Communications
Author-email: api@aweber.com
License: UNKNOWN
Platform: UNKNOWN
Classifier: Development Status :: 5 - Production/Stable
Classifier: Intended Audience :: Developers
Classifier: License :: OSI Approved :: BSD License
Classifier: Natural Language :: English
Classifier: Operating System :: OS Independent
Classifier: Programming Language :: Python :: 2
Classifier: Programming Language :: Python :: 2.6
Classifier: Programming Language :: Python :: 2.7
Classifier: Programming Language :: Python :: 3
Classifier: Programming Language :: Python :: 3.2
Classifier: Programming Language :: Python :: 3.3
Classifier: Programming Language :: Python :: 3.4
Classifier: Programming Language :: Python :: Implementation :: CPython
Requires-Dist: six (<2.0.0,>=1.7.2)
Provides-Extra: mongo
Requires-Dist: pymongo (<2.8,>=2.7); extra == 'mongo'
Provides-Extra: postgres
Requires-Dist: psycopg2 (<3.0,>=2.5); extra == 'postgres'
Provides-Extra: rabbit
Requires-Dist: requests (>=2.3); extra == 'rabbit'
Provides-Extra: tornado
Requires-Dist: tornado (>=3.1); extra == 'tornado'
